mugq/__init__.py
mugq/mugq.py
mugq-0.0.1.dist-info/LICENSE.txt
mugq-0.0.1.dist-info/METADATA
mugq-0.0.1.dist-info/WHEEL
mugq-0.0.1.dist-info/top_level.txt
mugq-0.0.1.dist-info/RECORD
