Metadata-Version: 2.1
Name: mugq
Version: 0.0.1
Summary: DESCRIPTION
Author-email: Dr Anna Sung and Prof Kelvin Leong <k.leong@chester.ac.uk>
License: BSD-3-Clause
Keywords: text classification,rating
Classifier: Programming Language :: Python :: 3
Classifier: License :: OSI Approved :: MIT License
Classifier: Operating System :: OS Independent
Requires-Python: >=3.8
License-File: LICENSE.txt
Requires-Dist: nltk
Requires-Dist: torch
Requires-Dist: transformers
Requires-Dist: csv
Requires-Dist: tabulate
Requires-Dist: pandas
Requires-Dist: openpyxl
Requires-Dist: scikit-learn
Requires-Dist: matplotlib
Requires-Dist: statsmodels
